artyompackage/__init__.py
artyompackage/first.py
artyompackage-1.0.dist-info/METADATA
artyompackage-1.0.dist-info/WHEEL
artyompackage-1.0.dist-info/top_level.txt
artyompackage-1.0.dist-info/RECORD
