Metadata-Version: 2.1
Name: artyompackage
Version: 1.0
Summary: Artyom package
Home-page: UNKNOWN
Author: Artyom Ashigov
Author-email: artyomashigov@gmail.com
License: MIT
Platform: UNKNOWN
